setup_example/__init__.py
setup_example/myfile.py
setup_example-0.1.dist-info/METADATA
setup_example-0.1.dist-info/WHEEL
setup_example-0.1.dist-info/entry_points.txt
setup_example-0.1.dist-info/top_level.txt
setup_example-0.1.dist-info/RECORD
