Metadata-Version: 2.1
Name: setup-example
Version: 0.1
Summary: UNKNOWN
Home-page: UNKNOWN
License: UNKNOWN
Platform: UNKNOWN
Requires-Dist: numpy
Requires-Dist: requests
